deprive/__init__.py
deprive/collect.py
deprive/handler.py
deprive/modifier.py
deprive/names.py
deprive/scope.py
deprive/tracker.py
deprive/visitor.py
deprive-0.3.0.dist-info/licenses/LICENSE
deprive-0.3.0.dist-info/METADATA
deprive-0.3.0.dist-info/WHEEL
deprive-0.3.0.dist-info/top_level.txt
deprive-0.3.0.dist-info/RECORD
