Metadata-Version: 2.4
Name: deprive
Version: 0.3.0
Summary: Generate dependency graphs and modify Python packages based on the generated graphs.
Author-email: Tim Hörmann <pypi@audivir.de>
License-Expression: MIT
Project-URL: Homepage, https://github.com/audivir/deprive
Project-URL: Repository, https://github.com/audivir/deprive
Requires-Python: >=3.9
License-File: LICENSE
Requires-Dist: libcst
Provides-Extra: dev
Requires-Dist: ruff; extra == "dev"
Requires-Dist: mypy; extra == "dev"
Requires-Dist: pytest; extra == "dev"
Requires-Dist: coverage[toml]; extra == "dev"
Requires-Dist: vulture; extra == "dev"
Dynamic: license-file
